hdlconv/__init__.py
hdlconv/core.py
hdlconv/slog2vlog.py
hdlconv/vhdl2vhdl.py
hdlconv/vhdl2vlog.py
hdlconv/templates/docker.jinja
hdlconv/templates/ghdl-yosys.jinja
hdlconv/templates/ghdl.jinja
hdlconv/templates/slang-yosys.jinja
hdlconv/templates/synlig.jinja
hdlconv/templates/yosys.jinja
hdlconv-0.3.0.dist-info/LICENSE
hdlconv-0.3.0.dist-info/METADATA
hdlconv-0.3.0.dist-info/WHEEL
hdlconv-0.3.0.dist-info/entry_points.txt
hdlconv-0.3.0.dist-info/top_level.txt
hdlconv-0.3.0.dist-info/RECORD
